{
  "ver": {
    "version": "1.0"
  },
  "screen": {
    "title": "No Name",
    "width": 1920,
    "height": 1080
  },
  "screenObjects": [
    {
      "type": "module",
      "title": "HUD Horizon V2",
      "x": -1,
      "y": 0,
      "width": 1918,
      "height": 1077,
      "grid_position": "MidM",
      "grid_percentage_x": 0.99375,
      "grid_percentage_y": 0.9916666666666667,
      "module": {
        "name": "HUD Horizon V2",
        "options": [
          {
            "name": "line_mode",
            "value": 1
          },
          {
            "name": "line_thickness",
            "value": 2
          },
          {
            "name": "MainColor",
            "value": [
              0,
              255,
              0
            ]
          },
          {
            "name": "flight_path_color",
            "value": [
              255,
              0,
              255
            ]
          },
          {
            "name": "show_targets",
            "value": true
          },
          {
            "name": "target_distance_threshold",
            "value": 10
          },
          {
            "name": "fov_x",
            "value": 20
          }
        ]
      },
      "id": "M_47zgz"
    },
    {
      "type": "module",
      "title": "Traffic Scope",
      "x": 1453,
      "y": 697,
      "width": 397,
      "height": 337,
      "grid_position": "BotR",
      "grid_percentage_x": 1.1609375,
      "grid_percentage_y": 0.8083333333333333,
      "module": {
        "name": "Traffic Scope",
        "options": [
          {
            "name": "show_callsign",
            "value": false
          },
          {
            "name": "show_details",
            "value": false
          },
          {
            "name": "details_offset",
            "value": 11
          },
          {
            "name": "target_show_lat_lon",
            "value": false
          },
          {
            "name": "scope_scale_miles",
            "value": 1
          },
          {
            "name": "draw_aircraft_icon",
            "value": true
          },
          {
            "name": "aircraft_icon_scale",
            "value": 10
          }
        ]
      },
      "id": "M_1p6h0"
    },
    {
      "type": "module",
      "title": "Text",
      "x": 1591,
      "y": 438,
      "width": 271,
      "height": 135,
      "grid_position": "MidR",
      "grid_percentage_x": 1.3953125,
      "grid_percentage_y": 0.8083333333333333,
      "module": {
        "name": "Text",
        "options": [
          {
            "name": "template",
            "value": ""
          },
          {
            "name": "text",
            "value": "{alt}"
          },
          {
            "name": "font_name",
            "value": "arial"
          },
          {
            "name": "font_size",
            "value": 111
          },
          {
            "name": "font_bold",
            "value": false
          },
          {
            "name": "text_color",
            "value": [
              200,
              255,
              255
            ]
          },
          {
            "name": "box_color",
            "value": [
              255,
              255,
              255
            ]
          },
          {
            "name": "box_weight",
            "value": 4
          },
          {
            "name": "box_radius",
            "value": 10
          }
        ]
      },
      "id": "M_ek5bh"
    },
    {
      "type": "module",
      "title": "HUD AOA",
      "x": 25,
      "y": 752,
      "width": 64,
      "height": 185,
      "grid_position": "BotL",
      "grid_percentage_x": 0.178125,
      "grid_percentage_y": 0.6916666666666667,
      "module": {
        "name": "HUD AOA",
        "options": [
          {
            "name": "showLDMax",
            "value": true
          },
          {
            "name": "aoa_color",
            "value": [
              255,
              255,
              255
            ]
          }
        ]
      },
      "id": "M_4jlto"
    },
    {
      "type": "module",
      "title": "HSI",
      "x": 781,
      "y": 656,
      "width": 300,
      "height": 315,
      "grid_position": "BotM",
      "grid_percentage_x": 0.909375,
      "grid_percentage_y": 0.5194444444444445,
      "module": {
        "name": "HSI",
        "options": [
          {
            "name": "hsi_size",
            "value": 300
          }
        ]
      },
      "id": "M_c1p1g"
    },
    {
      "type": "module",
      "title": "Wind",
      "x": 27,
      "y": 952,
      "width": 150,
      "height": 150,
      "grid_position": "BotL",
      "grid_percentage_x": 0.31875,
      "grid_percentage_y": 1.7055555555555555,
      "module": {
        "name": "Wind",
        "options": [
          {
            "name": "arrow_size",
            "value": 50
          }
        ]
      },
      "id": "M_94u5g"
    },
    {
      "type": "module",
      "title": "Slip Skid",
      "x": 823,
      "y": 1004,
      "width": 247,
      "height": 50,
      "grid_position": "BotM",
      "grid_percentage_x": 0.9578125,
      "grid_percentage_y": 1.7166666666666666,
      "module": {
        "name": "Slip Skid",
        "options": [
          {
            "name": "MainColor",
            "value": [
              255,
              255,
              255
            ]
          },
          {
            "name": "BallColor",
            "value": [
              255,
              255,
              255
            ]
          }
        ]
      },
      "id": "M_k1ag0"
    },
    {
      "type": "module",
      "title": "Heading",
      "x": 607,
      "y": 38,
      "width": 706,
      "height": 113,
      "grid_position": "TopM",
      "grid_percentage_x": 1.0,
      "grid_percentage_y": 0.525,
      "module": {
        "name": "Heading",
        "options": [
          {
            "name": "label_color",
            "value": [
              255,
              255,
              0
            ]
          },
          {
            "name": "font_color",
            "value": [
              255,
              255,
              255
            ]
          },
          {
            "name": "font1_size",
            "value": 20
          },
          {
            "name": "font2_size",
            "value": 30
          }
        ]
      },
      "id": "M_807dm"
    },
    {
      "type": "module",
      "title": "RollIndicator",
      "x": 755,
      "y": 611,
      "width": 500,
      "height": 500,
      "grid_position": "BotM",
      "grid_percentage_x": 1.140625,
      "grid_percentage_y": 0.7833333333333333,
      "module": {
        "name": "RollIndicator",
        "options": [
          {
            "name": "roll_point_size",
            "value": 20
          }
        ]
      },
      "id": "M_y06gj"
    },
    {
      "type": "module",
      "title": "HUD CDI",
      "x": 860,
      "y": 439,
      "width": 200,
      "height": 200,
      "grid_position": "MidM",
      "grid_percentage_x": 1.0,
      "grid_percentage_y": 0.9944444444444445,
      "module": {
        "name": "HUD CDI",
        "options": [
          {
            "name": "cdi_color",
            "value": [
              255,
              255,
              255
            ]
          }
        ]
      },
      "id": "M_mhfom"
    },
    {
      "type": "module",
      "title": "Text",
      "x": 891,
      "y": 13,
      "width": 76,
      "height": 40,
      "grid_position": "TopM",
      "grid_percentage_x": 0.903125,
      "grid_percentage_y": 0.18333333333333332,
      "module": {
        "name": "Text",
        "options": [
          {
            "name": "template",
            "value": ""
          },
          {
            "name": "text",
            "value": "{mag_head%.0f}"
          },
          {
            "name": "font_name",
            "value": "monospace"
          },
          {
            "name": "font_size",
            "value": 38
          },
          {
            "name": "font_bold",
            "value": false
          },
          {
            "name": "text_color",
            "value": [
              200,
              255,
              255
            ]
          },
          {
            "name": "box_color",
            "value": [
              255,
              255,
              255
            ]
          },
          {
            "name": "box_weight",
            "value": 0
          },
          {
            "name": "box_radius",
            "value": 0
          }
        ]
      },
      "id": "M_yloh7"
    },
    {
      "type": "module",
      "title": "Text",
      "x": 1622,
      "y": 568,
      "width": 200,
      "height": 50,
      "grid_position": "MidR",
      "grid_percentage_x": 1.38125,
      "grid_percentage_y": 1.2944444444444445,
      "module": {
        "name": "Text",
        "options": [
          {
            "name": "template",
            "value": ""
          },
          {
            "name": "text",
            "value": "{sys_time_string}"
          },
          {
            "name": "font_name",
            "value": "monospace"
          },
          {
            "name": "font_size",
            "value": 34
          },
          {
            "name": "font_bold",
            "value": false
          },
          {
            "name": "text_color",
            "value": [
              200,
              255,
              255
            ]
          },
          {
            "name": "box_color",
            "value": [
              255,
              255,
              255
            ]
          },
          {
            "name": "box_weight",
            "value": 0
          },
          {
            "name": "box_radius",
            "value": 0
          }
        ]
      },
      "id": "M_iryla"
    },
    {
      "type": "module",
      "title": "Buoy Manager",
      "x": 5,
      "y": 3,
      "width": 377,
      "height": 280,
      "grid_position": "TopL",
      "grid_percentage_x": 0.6046875,
      "grid_percentage_y": 0.7944444444444444,
      "module": {
        "name": "Buoy Manager",
        "options": [
          {
            "name": "target_font_size",
            "value": 20
          },
          {
            "name": "buoyDistance",
            "value": 10
          },
          {
            "name": "buoyAlt",
            "value": -500
          }
        ]
      },
      "id": "M_u34tl"
    },
    {
      "type": "module",
      "title": "object 3D",
      "x": 1563,
      "y": 6,
      "width": 288,
      "height": 282,
      "grid_position": "TopR",
      "grid_percentage_x": 1.334375,
      "grid_percentage_y": 0.8166666666666667,
      "module": {
        "name": "object 3D",
        "options": [
          {
            "name": "MainColor",
            "value": [
              255,
              255,
              255
            ]
          }
        ]
      },
      "id": "M_unk15"
    },
    {
      "type": "module",
      "title": "Text",
      "x": 1845,
      "y": 532,
      "width": 63,
      "height": 40,
      "grid_position": "MidR",
      "grid_percentage_x": 1.8640625,
      "grid_percentage_y": 1.0666666666666667,
      "module": {
        "name": "Text",
        "options": [
          {
            "name": "template",
            "value": ""
          },
          {
            "name": "text",
            "value": "ft"
          },
          {
            "name": "font_name",
            "value": "monospace"
          },
          {
            "name": "font_size",
            "value": 30
          },
          {
            "name": "font_bold",
            "value": false
          },
          {
            "name": "text_color",
            "value": [
              200,
              255,
              255
            ]
          },
          {
            "name": "box_color",
            "value": [
              255,
              255,
              255
            ]
          },
          {
            "name": "box_weight",
            "value": 0
          },
          {
            "name": "box_radius",
            "value": 0
          }
        ]
      },
      "id": "M_vtx42"
    },
    {
      "type": "module",
      "title": "Text",
      "x": 1577,
      "y": 312,
      "width": 217,
      "height": 40,
      "grid_position": "TopR",
      "grid_percentage_x": 1.2671875,
      "grid_percentage_y": 1.8444444444444446,
      "module": {
        "name": "Text",
        "options": [
          {
            "name": "template",
            "value": "pitch"
          },
          {
            "name": "text",
            "value": "pitch: {pitch%0.1f}"
          },
          {
            "name": "font_name",
            "value": "monospace"
          },
          {
            "name": "font_size",
            "value": 30
          },
          {
            "name": "font_bold",
            "value": false
          },
          {
            "name": "text_color",
            "value": [
              200,
              255,
              255
            ]
          },
          {
            "name": "box_color",
            "value": [
              255,
              255,
              255
            ]
          },
          {
            "name": "box_weight",
            "value": 0
          },
          {
            "name": "box_radius",
            "value": 0
          }
        ]
      },
      "id": "M_7otcl"
    },
    {
      "type": "module",
      "title": "Text",
      "x": 1594,
      "y": 348,
      "width": 197,
      "height": 40,
      "grid_position": "MidR",
      "grid_percentage_x": 1.2890625,
      "grid_percentage_y": 0.044444444444444446,
      "module": {
        "name": "Text",
        "options": [
          {
            "name": "template",
            "value": "pitch"
          },
          {
            "name": "text",
            "value": "roll: {roll%0.1f}"
          },
          {
            "name": "font_name",
            "value": "monospace"
          },
          {
            "name": "font_size",
            "value": 30
          },
          {
            "name": "font_bold",
            "value": false
          },
          {
            "name": "text_color",
            "value": [
              200,
              255,
              255
            ]
          },
          {
            "name": "box_color",
            "value": [
              255,
              255,
              255
            ]
          },
          {
            "name": "box_weight",
            "value": 0
          },
          {
            "name": "box_radius",
            "value": 0
          }
        ]
      },
      "id": "M_e6x39"
    },
    {
      "type": "module",
      "title": "Text",
      "x": 1612,
      "y": 382,
      "width": 200,
      "height": 50,
      "grid_position": "MidR",
      "grid_percentage_x": 1.35,
      "grid_percentage_y": 0.2611111111111111,
      "module": {
        "name": "Text",
        "options": [
          {
            "name": "template",
            "value": "pitch"
          },
          {
            "name": "text",
            "value": "yaw: {mag_head%0.1f}"
          },
          {
            "name": "font_name",
            "value": "monospace"
          },
          {
            "name": "font_size",
            "value": 30
          },
          {
            "name": "font_bold",
            "value": false
          },
          {
            "name": "text_color",
            "value": [
              200,
              255,
              255
            ]
          },
          {
            "name": "box_color",
            "value": [
              255,
              255,
              255
            ]
          },
          {
            "name": "box_weight",
            "value": 0
          },
          {
            "name": "box_radius",
            "value": 0
          }
        ]
      },
      "id": "M_97g1b"
    },
    {
      "type": "group",
      "title": "Group_24",
      "x": 23,
      "y": 407,
      "width": 259,
      "height": 241,
      "grid_position": "MidL",
      "grid_percentage_x": 0.4765625,
      "grid_percentage_y": 0.9305555555555556,
      "screenObjects": [
        {
          "type": "module",
          "title": "Text",
          "x": 59,
          "y": 407,
          "width": 130,
          "height": 34,
          "grid_position": "MidL",
          "grid_percentage_x": 0.3875,
          "grid_percentage_y": 0.35555555555555557,
          "module": {
            "name": "Text",
            "options": [
              {
                "name": "template",
                "value": ""
              },
              {
                "name": "text",
                "value": "TAS {tas%.0f}"
              },
              {
                "name": "font_name",
                "value": "monospace"
              },
              {
                "name": "font_size",
                "value": 30
              },
              {
                "name": "font_bold",
                "value": false
              },
              {
                "name": "text_color",
                "value": [
                  200,
                  255,
                  255
                ]
              },
              {
                "name": "box_color",
                "value": [
                  255,
                  255,
                  255
                ]
              },
              {
                "name": "box_weight",
                "value": 0
              },
              {
                "name": "box_radius",
                "value": 0
              }
            ]
          },
          "id": "M_kom5v"
        },
        {
          "type": "module",
          "title": "Text",
          "x": 23,
          "y": 436,
          "width": 197,
          "height": 132,
          "grid_position": "MidL",
          "grid_percentage_x": 0.3796875,
          "grid_percentage_y": 0.7888888888888889,
          "module": {
            "name": "Text",
            "options": [
              {
                "name": "template",
                "value": ""
              },
              {
                "name": "text",
                "value": "{ias%.0f}"
              },
              {
                "name": "font_name",
                "value": "arial"
              },
              {
                "name": "font_size",
                "value": 115
              },
              {
                "name": "font_bold",
                "value": false
              },
              {
                "name": "text_color",
                "value": [
                  200,
                  255,
                  255
                ]
              },
              {
                "name": "box_color",
                "value": [
                  255,
                  255,
                  255
                ]
              },
              {
                "name": "box_weight",
                "value": 4
              },
              {
                "name": "box_radius",
                "value": 10
              }
            ]
          },
          "id": "M_sex7a"
        },
        {
          "type": "module",
          "title": "Text",
          "x": 221,
          "y": 536,
          "width": 61,
          "height": 34,
          "grid_position": "MidL",
          "grid_percentage_x": 0.7859375,
          "grid_percentage_y": 1.0722222222222222,
          "module": {
            "name": "Text",
            "options": [
              {
                "name": "template",
                "value": ""
              },
              {
                "name": "text",
                "value": "mph"
              },
              {
                "name": "font_name",
                "value": "monospace"
              },
              {
                "name": "font_size",
                "value": 30
              },
              {
                "name": "font_bold",
                "value": false
              },
              {
                "name": "text_color",
                "value": [
                  200,
                  255,
                  255
                ]
              },
              {
                "name": "box_color",
                "value": [
                  255,
                  255,
                  255
                ]
              },
              {
                "name": "box_weight",
                "value": 0
              },
              {
                "name": "box_radius",
                "value": 0
              }
            ]
          },
          "id": "M_41x1a"
        },
        {
          "type": "module",
          "title": "Text",
          "x": 45,
          "y": 569,
          "width": 102,
          "height": 27,
          "grid_position": "MidL",
          "grid_percentage_x": 0.3,
          "grid_percentage_y": 1.2361111111111112,
          "module": {
            "name": "Text",
            "options": [
              {
                "name": "template",
                "value": ""
              },
              {
                "name": "text",
                "value": "GS {gndspeed%.0f}"
              },
              {
                "name": "font_name",
                "value": "monospace"
              },
              {
                "name": "font_size",
                "value": 26
              },
              {
                "name": "font_bold",
                "value": false
              },
              {
                "name": "text_color",
                "value": [
                  200,
                  255,
                  255
                ]
              },
              {
                "name": "box_color",
                "value": [
                  255,
                  255,
                  255
                ]
              },
              {
                "name": "box_weight",
                "value": 0
              },
              {
                "name": "box_radius",
                "value": 0
              }
            ]
          },
          "id": "M_5kdua"
        },
        {
          "type": "module",
          "title": "Text",
          "x": 45,
          "y": 598,
          "width": 79,
          "height": 22,
          "grid_position": "MidL",
          "grid_percentage_x": 0.2640625,
          "grid_percentage_y": 1.3833333333333333,
          "module": {
            "name": "Text",
            "options": [
              {
                "name": "template",
                "value": ""
              },
              {
                "name": "text",
                "value": "{oat} OAT"
              },
              {
                "name": "font_name",
                "value": "monospace"
              },
              {
                "name": "font_size",
                "value": 20
              },
              {
                "name": "font_bold",
                "value": false
              },
              {
                "name": "text_color",
                "value": [
                  200,
                  255,
                  255
                ]
              },
              {
                "name": "box_color",
                "value": [
                  255,
                  255,
                  255
                ]
              },
              {
                "name": "box_weight",
                "value": 0
              },
              {
                "name": "box_radius",
                "value": 0
              }
            ]
          },
          "id": "M_tpl7b"
        },
        {
          "type": "module",
          "title": "Text",
          "x": 45,
          "y": 622,
          "width": 86,
          "height": 26,
          "grid_position": "MidL",
          "grid_percentage_x": 0.275,
          "grid_percentage_y": 1.5277777777777777,
          "module": {
            "name": "Text",
            "options": [
              {
                "name": "template",
                "value": ""
              },
              {
                "name": "text",
                "value": "G's {vert_G}"
              },
              {
                "name": "font_name",
                "value": "monospace"
              },
              {
                "name": "font_size",
                "value": 20
              },
              {
                "name": "font_bold",
                "value": false
              },
              {
                "name": "text_color",
                "value": [
                  200,
                  255,
                  255
                ]
              },
              {
                "name": "box_color",
                "value": [
                  255,
                  255,
                  255
                ]
              },
              {
                "name": "box_weight",
                "value": 0
              },
              {
                "name": "box_radius",
                "value": 0
              }
            ]
          },
          "id": "M_lpk54"
        }
      ],
      "id": "M_kaqw5"
    }
  ]
}